{
  "version": 1,
  "createdAt": "2026-04-06T12:41:38.723Z",
  "source": "studio",
  "targetRepo": {
    "owner": "IT-NuanxinPro",
    "repo": "nuanXinProPic",
    "branch": "main"
  },
  "images": [
    {
      "series": "mobile",
      "relativePath": "wallpaper/mobile/人像/清新/20260406195831.jpeg",
      "category": "人像",
      "subcategory": "清新",
      "filename": "20260406195831.jpeg",
      "createdAt": "2026-04-06T12:41:38.723Z",
      "size": 1111253,
      "format": "jpeg",
      "ai": {
        "series": "mobile",
        "category": "人像",
        "subcategory": "清新",
        "primary": "mobile",
        "secondary": "人像",
        "third": "清新",
        "keywords": [
          "清新",
          "少女",
          "长发",
          "微笑"
        ],
        "description": "一位面带微笑的少女坐在沙发上，享受温暖的晨光。",
        "filenameSuggestions": [
          "坐在沙发上的清新少女.jpg",
          "微笑的长发女孩在温暖的客厅.jpg"
        ],
        "displayTitle": "微笑的少女在晨光中",
        "confidence": 0.9,
        "reasoning": "根据图片特征，人物面带甜美微笑，背景简洁光线明亮，符合【清新】(Fresh)的定义。"
      }
    },
    {
      "series": "mobile",
      "relativePath": "wallpaper/mobile/动漫/斗破苍穹/20260406201704.png",
      "category": "动漫",
      "subcategory": "斗破苍穹",
      "filename": "20260406201704.png",
      "createdAt": "2026-04-06T12:41:38.723Z",
      "size": 2005722,
      "format": "png",
      "ai": {
        "series": "mobile",
        "primary": "mobile",
        "secondary": "动漫",
        "category": "动漫",
        "third": "斗破苍穹",
        "subcategory": "斗破苍穹",
        "filenameSuggestions": [
          "身穿红色金边服饰的美杜莎.jpg",
          "金色皇冠下的美杜莎.jpg"
        ],
        "filenames": [
          "身穿红色金边服饰的美杜莎.jpg",
          "金色皇冠下的美杜莎.jpg"
        ],
        "displayTitle": "金色皇冠下美杜莎神秘少女",
        "keywords": [
          "美杜莎",
          "国风",
          "斗破苍穹"
        ],
        "description": "华丽红金服饰的美杜莎，头戴金色皇冠，充满神秘与高贵的气质。",
        "confidence": 0.9,
        "reasoning": "图片展示了一位少女，拥有精致的插画风格，服饰和配饰具有明显的中国风设计，如金色皇冠和红金配色的服饰。少女的整体形象充满国风特色，且并非动漫或游戏角色截图，因此归类为插画/国风。"
      }
    },
    {
      "series": "mobile",
      "relativePath": "wallpaper/mobile/插画/风景/20260406201625.jpeg",
      "category": "插画",
      "subcategory": "风景",
      "filename": "20260406201625.jpeg",
      "createdAt": "2026-04-06T12:41:38.723Z",
      "size": 650619,
      "format": "jpeg",
      "ai": {
        "series": "mobile",
        "primary": "mobile",
        "secondary": "插画",
        "category": "插画",
        "third": "风景",
        "subcategory": "风景",
        "filenameSuggestions": [
          "日落前的城市斜坡小径.jpg",
          "斜坡上的城市街道景象.jpg"
        ],
        "filenames": [
          "日落前的城市斜坡小径.jpg",
          "斜坡上的城市街道景象.jpg"
        ],
        "displayTitle": "日落前的城市斜坡小径",
        "keywords": [
          "城市",
          "插画",
          "街道",
          "日落"
        ],
        "description": "城市中一条充满生机的斜坡小径，日落时分景色尤为迷人。",
        "confidence": 0.9,
        "reasoning": "图片显示了一条城市斜坡小径，两边有房屋、绿植和电线杆，带有明显的城市风景特征，根据现有分类体系，归入风景/城市。"
      }
    },
    {
      "series": "mobile",
      "relativePath": "wallpaper/mobile/人像/清新/20260406201611.jpeg",
      "category": "人像",
      "subcategory": "清新",
      "filename": "20260406201611.jpeg",
      "createdAt": "2026-04-06T12:41:38.723Z",
      "size": 1057044,
      "format": "jpeg",
      "ai": {
        "series": "mobile",
        "category": "人像",
        "subcategory": "清新",
        "primary": "mobile",
        "secondary": "人像",
        "third": "清新",
        "keywords": [
          "清新",
          "阳光",
          "少女",
          "蓝天"
        ],
        "description": "阳光照耀下的美丽少女，仰望蓝天，展现清新自然之美。",
        "filenameSuggestions": [
          "阳光下的轻盈少女.jpg",
          "仰望天空的短发女孩.jpg"
        ],
        "displayTitle": "阳光下的轻盈少女",
        "confidence": 0.9,
        "reasoning": "图片中少女穿着轻盈的衣服，站在明亮的阳光下，背景是蓝天白云，整体氛围明亮且治愈，符合【清新】(Fresh)的定义。"
      }
    }
  ]
}